CHANGELOG.rst
MANIFEST.in
README.rst
VERSION.txt
setup.py
djangohmac/__init__.py
djangohmac/decorators.py
djangohmac/middleware.py
djangohmac/sign.py
djangohmac.egg-info/PKG-INFO
djangohmac.egg-info/SOURCES.txt
djangohmac.egg-info/dependency_links.txt
djangohmac.egg-info/requires.txt
djangohmac.egg-info/top_level.txt